<?xml version="1.0" encoding="UTF-8" ?>
<pageDefinition xmlns="http://xmlns.oracle.com/adfm/uimodel" version="12.2.1.11.57" id="Quality_InspectionPageDef"
                Package="Fragments.Modules.Inventory">
  <parameters/>
  <executables>
    <variableIterator id="variables"/>
    <iterator Binds="USERS_CRUD_OPERATIONS1" RangeSize="25" DataControl="AppModuleDataControl"
              id="USERS_CRUD_OPERATIONS1Iterator"/>
    <iterator Binds="TblInvVoucherMasterINV1" RangeSize="8" DataControl="AppModuleDataControl1"
              id="TblInvVoucherMasterINV1Iterator"/>
    <searchRegion Binds="TblInvVoucherMasterINV1Iterator" Criteria=""
                  Customizer="oracle.jbo.uicli.binding.JUSearchBindingCustomizer" id="TblInvVoucherMasterINV1Query"/>
    <iterator Binds="TblInvVoucherDetailView6" RangeSize="8" DataControl="AppModuleDataControl1"
              id="TblInvVoucherDetailView6Iterator"/>
    <searchRegion Binds="TblInvVoucherDetailView6Iterator" Criteria=""
                  Customizer="oracle.jbo.uicli.binding.JUSearchBindingCustomizer" id="TblInvVoucherDetailView6Query"/>
  </executables>
  <bindings>
    <tree IterBinding="USERS_CRUD_OPERATIONS1Iterator" id="USERS_CRUD_OPERATIONS1">
      <nodeDefinition DefName="model.UserRole.VO.USERS_CRUD_OPERATIONS" Name="USERS_CRUD_OPERATIONS10">
        <AttrNames>
          <Item Value="Crudid"/>
          <Item Value="Operation"/>
          <Item Value="Icon"/>
          <Item Value="Bindingname"/>
          <Item Value="Btndisabled"/>
        </AttrNames>
      </nodeDefinition>
    </tree>
    <attributeValues IterBinding="TblInvVoucherMasterINV1Iterator" id="Dated">
      <AttrNames>
        <Item Value="Dated"/>
      </AttrNames>
    </attributeValues>
    <list IterBinding="TblInvVoucherMasterINV1Iterator" StaticList="false" Uses="LOV_DepartmentId" id="DepartmentId"
          DTSupportsMRU="false" SelectItemValueMode="ListObject"/>
    <attributeValues IterBinding="TblInvVoucherMasterINV1Iterator" id="DoNo">
      <AttrNames>
        <Item Value="DoNo"/>
      </AttrNames>
    </attributeValues>
    <attributeValues IterBinding="TblInvVoucherMasterINV1Iterator" id="Id">
      <AttrNames>
        <Item Value="Id"/>
      </AttrNames>
    </attributeValues>
    <attributeValues IterBinding="TblInvVoucherMasterINV1Iterator" id="IgpNo">
      <AttrNames>
        <Item Value="IgpNo"/>
      </AttrNames>
    </attributeValues>
    <attributeValues IterBinding="TblInvVoucherMasterINV1Iterator" id="Narration">
      <AttrNames>
        <Item Value="Narration"/>
      </AttrNames>
    </attributeValues>
    <attributeValues IterBinding="TblInvVoucherMasterINV1Iterator" id="PoNo">
      <AttrNames>
        <Item Value="PoNo"/>
      </AttrNames>
    </attributeValues>
    <attributeValues IterBinding="TblInvVoucherMasterINV1Iterator" id="Vno">
      <AttrNames>
        <Item Value="Vno"/>
      </AttrNames>
    </attributeValues>
    <list IterBinding="TblInvVoucherMasterINV1Iterator" StaticList="false" Uses="LOV_Vtp" id="Vtp"
          DTSupportsMRU="false" SelectItemValueMode="ListObject"/>
    <list IterBinding="TblInvVoucherMasterINV1Iterator" StaticList="false" Uses="LOV_ProjectId" id="ProjectId"
          DTSupportsMRU="false" SelectItemValueMode="ListObject"/>
    <action IterBinding="TblInvVoucherMasterINV1Iterator" id="First" RequiresUpdateModel="true" Action="first"/>
    <action IterBinding="TblInvVoucherMasterINV1Iterator" id="Previous" RequiresUpdateModel="true" Action="previous"/>
    <action IterBinding="TblInvVoucherMasterINV1Iterator" id="Next" RequiresUpdateModel="true" Action="next"/>
    <action IterBinding="TblInvVoucherMasterINV1Iterator" id="Last" RequiresUpdateModel="true" Action="last"/>
    <action IterBinding="TblInvVoucherMasterINV1Iterator" id="CreateInsert" RequiresUpdateModel="true"
            Action="createInsertRow"/>
    <action IterBinding="TblInvVoucherMasterINV1Iterator" id="Execute" RequiresUpdateModel="true"
            Action="iteratorExecute"/>
    <action IterBinding="TblInvVoucherMasterINV1Iterator" id="Delete" RequiresUpdateModel="false"
            Action="removeCurrentRow"/>
    <action id="Commit" RequiresUpdateModel="true" Action="commitTransaction" DataControl="AppModuleDataControl1"/>
    <action id="Rollback" RequiresUpdateModel="false" Action="rollbackTransaction" DataControl="AppModuleDataControl1"/>
    <tree IterBinding="TblInvVoucherMasterINV1Iterator" id="TblInvVoucherMasterINV1">
      <nodeDefinition DefName="model.ERP.VO.TblInvVoucherMasterINV" Name="TblInvVoucherMasterINV10">
        <AttrNames>
          <Item Value="Carrier"/>
          <Item Value="Dated"/>
          <Item Value="DepartmentId"/>
          <Item Value="DoNo"/>
          <Item Value="Id"/>
          <Item Value="IgpNo"/>
          <Item Value="Narration"/>
          <Item Value="NetAmount"/>
          <Item Value="PblSuppId"/>
          <Item Value="PoNo"/>
          <Item Value="QcNo"/>
          <Item Value="Vno"/>
          <Item Value="Vtp"/>
          <Item Value="ProjectId"/>
        </AttrNames>
      </nodeDefinition>
    </tree>
    <tree IterBinding="TblInvVoucherDetailView6Iterator" id="TblInvVoucherDetailView6">
      <nodeDefinition DefName="model.ERP.VO.TblInvVoucherDetailView" Name="TblInvVoucherDetailView60">
        <AttrNames>
          <Item Value="Id"/>
          <Item Value="InvVoucherMasterId"/>
          <Item Value="SrNo"/>
          <Item Value="ItemL4Id"/>
          <Item Value="UomId"/>
          <Item Value="Description"/>
          <Item Value="Qty"/>
          <Item Value="DoQty"/>
          <Item Value="PoQty"/>
          <Item Value="IgpQty"/>
          <Item Value="QcQty"/>
          <Item Value="GrnQty"/>
          <Item Value="Rate"/>
          <Item Value="Amount"/>
        </AttrNames>
      </nodeDefinition>
    </tree>
    <action IterBinding="TblInvVoucherDetailView6Iterator" id="CreateInsert1" RequiresUpdateModel="true"
            Action="createInsertRow"/>
    <action IterBinding="TblInvVoucherDetailView6Iterator" id="Execute1" RequiresUpdateModel="true"
            Action="iteratorExecute"/>
    <action IterBinding="TblInvVoucherDetailView6Iterator" id="Delete1" RequiresUpdateModel="false"
            Action="removeCurrentRow"/>
    <attributeValues IterBinding="TblInvVoucherMasterINV1Iterator" id="Vtp1">
      <AttrNames>
        <Item Value="Vtp"/>
      </AttrNames>
    </attributeValues>
  </bindings>
</pageDefinition>
